discord_android/__init__.py
discord_android/identify.py
discord_android-1.1.0.dist-info/LICENSE
discord_android-1.1.0.dist-info/METADATA
discord_android-1.1.0.dist-info/WHEEL
discord_android-1.1.0.dist-info/top_level.txt
discord_android-1.1.0.dist-info/RECORD
